byted_barocket-0.1.3.dist-info/METADATA
byted_barocket-0.1.3.dist-info/WHEEL
ba_rocket.libs/libcrypto-cde898ee.so.1.1
ba_rocket.libs/libssl-f39abf7f.so.1.1
ba_rocket/__init__.py
ba_rocket/ba_rocket.cpython-310-x86_64-linux-gnu.so
byted_barocket-0.1.3.dist-info/RECORD
